{"title":"Sample Gen","fileName":"sample-gen.json","matchType":"CLASSIFIED_DOUBLES","status":"DRAWN","doubleElimination":false,"teams":[{"teamNumber":1,"players":[{"firstName":"33","lastName":"","rated":false},{"firstName":"17","lastName":"","rated":true}],"history":[]},{"teamNumber":2,"players":[{"firstName":"68","lastName":"","rated":false},{"firstName":"2","lastName":"","rated":true}],"history":[]},{"teamNumber":3,"players":[{"firstName":"34","lastName":"","rated":false},{"firstName":"12","lastName":"","rated":true}],"history":[]},{"teamNumber":4,"players":[{"firstName":"78","lastName":"","rated":false},{"firstName":"19","lastName":"","rated":true}],"history":[]},{"teamNumber":5,"players":[{"firstName":"51","lastName":"","rated":false},{"firstName":"9","lastName":"","rated":true}],"history":[]},{"teamNumber":6,"players":[{"firstName":"46","lastName":"","rated":false},{"firstName":"3","lastName":"","rated":true}],"history":[]},{"teamNumber":7,"players":[{"firstName":"59","lastName":"","rated":false},{"firstName":"20","lastName":"","rated":true}],"history":[]},{"teamNumber":8,"players":[{"firstName":"31","lastName":"","rated":false},{"firstName":"16","lastName":"","rated":true}],"history":[]},{"teamNumber":9,"players":[{"firstName":"21","lastName":"","rated":false},{"firstName":"4","lastName":"","rated":true}],"history":[]},{"teamNumber":10,"players":[{"firstName":"70","lastName":"","rated":false},{"firstName":"18","lastName":"","rated":true}],"history":[]},{"teamNumber":11,"players":[{"firstName":"53","lastName":"","rated":false},{"firstName":"11","lastName":"","rated":true}],"history":[]},{"teamNumber":12,"players":[{"firstName":"37","lastName":"","rated":false},{"firstName":"6","lastName":"","rated":true}],"history":[]},{"teamNumber":13,"players":[{"firstName":"63","lastName":"","rated":false},{"firstName":"13","lastName":"","rated":true}],"history":[]},{"teamNumber":14,"players":[{"firstName":"25","lastName":"","rated":false},{"firstName":"1","lastName":"","rated":true}],"history":[]},{"teamNumber":15,"players":[{"firstName":"30","lastName":"","rated":false},{"firstName":"8","lastName":"","rated":true}],"history":[]},{"teamNumber":16,"players":[{"firstName":"26","lastName":"","rated":false},{"firstName":"10","lastName":"","rated":true}],"history":[]},{"teamNumber":17,"players":[{"firstName":"72","lastName":"","rated":false},{"firstName":"7","lastName":"","rated":true}],"history":[]},{"teamNumber":18,"players":[{"firstName":"49","lastName":"","rated":false},{"firstName":"5","lastName":"","rated":true}],"history":[]},{"teamNumber":19,"players":[{"firstName":"23","lastName":"","rated":false},{"firstName":"14","lastName":"","rated":true}],"history":[]},{"teamNumber":20,"players":[{"firstName":"80","lastName":"","rated":false},{"firstName":"15","lastName":"","rated":true}],"history":[]},{"teamNumber":21,"players":[{"firstName":"55","lastName":"","rated":false},{"firstName":"62","lastName":"","rated":false}],"history":[]},{"teamNumber":22,"players":[{"firstName":"48","lastName":"","rated":false},{"firstName":"76","lastName":"","rated":false}],"history":[]},{"teamNumber":23,"players":[{"firstName":"40","lastName":"","rated":false},{"firstName":"73","lastName":"","rated":false}],"history":[]},{"teamNumber":24,"players":[{"firstName":"74","lastName":"","rated":false},{"firstName":"58","lastName":"","rated":false}],"history":[]},{"teamNumber":25,"players":[{"firstName":"66","lastName":"","rated":false},{"firstName":"61","lastName":"","rated":false}],"history":[]},{"teamNumber":26,"players":[{"firstName":"57","lastName":"","rated":false},{"firstName":"77","lastName":"","rated":false}],"history":[]},{"teamNumber":27,"players":[{"firstName":"28","lastName":"","rated":false},{"firstName":"65","lastName":"","rated":false}],"history":[]},{"teamNumber":28,"players":[{"firstName":"75","lastName":"","rated":false},{"firstName":"45","lastName":"","rated":false}],"history":[]},{"teamNumber":29,"players":[{"firstName":"38","lastName":"","rated":false},{"firstName":"32","lastName":"","rated":false}],"history":[]},{"teamNumber":30,"players":[{"firstName":"47","lastName":"","rated":false},{"firstName":"67","lastName":"","rated":false}],"history":[]},{"teamNumber":31,"players":[{"firstName":"50","lastName":"","rated":false},{"firstName":"44","lastName":"","rated":false}],"history":[]},{"teamNumber":32,"players":[{"firstName":"79","lastName":"","rated":false},{"firstName":"41","lastName":"","rated":false}],"history":[]},{"teamNumber":33,"players":[{"firstName":"22","lastName":"","rated":false},{"firstName":"71","lastName":"","rated":false}],"history":[]},{"teamNumber":34,"players":[{"firstName":"52","lastName":"","rated":false},{"firstName":"39","lastName":"","rated":false}],"history":[]},{"teamNumber":35,"players":[{"firstName":"69","lastName":"","rated":false},{"firstName":"29","lastName":"","rated":false}],"history":[]},{"teamNumber":36,"players":[{"firstName":"60","lastName":"","rated":false},{"firstName":"35","lastName":"","rated":false}],"history":[]},{"teamNumber":37,"players":[{"firstName":"24","lastName":"","rated":false},{"firstName":"64","lastName":"","rated":false}],"history":[]},{"teamNumber":38,"players":[{"firstName":"27","lastName":"","rated":false},{"firstName":"43","lastName":"","rated":false}],"history":[]},{"teamNumber":39,"players":[{"firstName":"54","lastName":"","rated":false},{"firstName":"56","lastName":"","rated":false}],"history":[]},{"teamNumber":40,"players":[{"firstName":"42","lastName":"","rated":false},{"firstName":"36","lastName":"","rated":false}],"history":[]}],"players":[{"firstName":"1","lastName":"","rated":true},{"firstName":"2","lastName":"","rated":true},{"firstName":"3","lastName":"","rated":true},{"firstName":"4","lastName":"","rated":true},{"firstName":"5","lastName":"","rated":true},{"firstName":"6","lastName":"","rated":true},{"firstName":"7","lastName":"","rated":true},{"firstName":"8","lastName":"","rated":true},{"firstName":"9","lastName":"","rated":true},{"firstName":"10","lastName":"","rated":true},{"firstName":"11","lastName":"","rated":true},{"firstName":"12","lastName":"","rated":true},{"firstName":"13","lastName":"","rated":true},{"firstName":"14","lastName":"","rated":true},{"firstName":"15","lastName":"","rated":true},{"firstName":"16","lastName":"","rated":true},{"firstName":"17","lastName":"","rated":true},{"firstName":"18","lastName":"","rated":true},{"firstName":"19","lastName":"","rated":true},{"firstName":"20","lastName":"","rated":true},{"firstName":"21","lastName":"","rated":false},{"firstName":"22","lastName":"","rated":false},{"firstName":"23","lastName":"","rated":false},{"firstName":"24","lastName":"","rated":false},{"firstName":"25","lastName":"","rated":false},{"firstName":"26","lastName":"","rated":false},{"firstName":"27","lastName":"","rated":false},{"firstName":"28","lastName":"","rated":false},{"firstName":"29","lastName":"","rated":false},{"firstName":"30","lastName":"","rated":false},{"firstName":"31","lastName":"","rated":false},{"firstName":"32","lastName":"","rated":false},{"firstName":"33","lastName":"","rated":false},{"firstName":"34","lastName":"","rated":false},{"firstName":"35","lastName":"","rated":false},{"firstName":"36","lastName":"","rated":false},{"firstName":"37","lastName":"","rated":false},{"firstName":"38","lastName":"","rated":false},{"firstName":"39","lastName":"","rated":false},{"firstName":"40","lastName":"","rated":false},{"firstName":"41","lastName":"","rated":false},{"firstName":"42","lastName":"","rated":false},{"firstName":"43","lastName":"","rated":false},{"firstName":"44","lastName":"","rated":false},{"firstName":"45","lastName":"","rated":false},{"firstName":"46","lastName":"","rated":false},{"firstName":"47","lastName":"","rated":false},{"firstName":"48","lastName":"","rated":false},{"firstName":"49","lastName":"","rated":false},{"firstName":"50","lastName":"","rated":false},{"firstName":"51","lastName":"","rated":false},{"firstName":"52","lastName":"","rated":false},{"firstName":"53","lastName":"","rated":false},{"firstName":"54","lastName":"","rated":false},{"firstName":"55","lastName":"","rated":false},{"firstName":"56","lastName":"","rated":false},{"firstName":"57","lastName":"","rated":false},{"firstName":"58","lastName":"","rated":false},{"firstName":"59","lastName":"","rated":false},{"firstName":"60","lastName":"","rated":false},{"firstName":"61","lastName":"","rated":false},{"firstName":"62","lastName":"","rated":false},{"firstName":"63","lastName":"","rated":false},{"firstName":"64","lastName":"","rated":false},{"firstName":"65","lastName":"","rated":false},{"firstName":"66","lastName":"","rated":false},{"firstName":"67","lastName":"","rated":false},{"firstName":"68","lastName":"","rated":false},{"firstName":"69","lastName":"","rated":false},{"firstName":"70","lastName":"","rated":false},{"firstName":"71","lastName":"","rated":false},{"firstName":"72","lastName":"","rated":false},{"firstName":"73","lastName":"","rated":false},{"firstName":"74","lastName":"","rated":false},{"firstName":"75","lastName":"","rated":false},{"firstName":"76","lastName":"","rated":false},{"firstName":"77","lastName":"","rated":false},{"firstName":"78","lastName":"","rated":false},{"firstName":"79","lastName":"","rated":false},{"firstName":"80","lastName":"","rated":false}]}