{"title":"Sampe 2","fileName":"sampe-2.json","matchType":"CLASSIFIED_DOUBLES","status":"STARTED","doubleElimination":false,"teams":[{"teamNumber":1,"players":[{"firstName":"George Ponce / Ricky ","lastName":"Mijares","rated":false},{"firstName":"Rogel ","lastName":"Carreon","rated":false}],"history":[]},{"teamNumber":2,"players":[{"firstName":"Cesar ","lastName":"Visitacion","rated":false},{"firstName":"Sam ","lastName":"Cadiente","rated":false}],"history":[]},{"teamNumber":3,"players":[{"firstName":"Sonny Regidor / Alain ","lastName":"Abiabi","rated":false},{"firstName":"Joel Solis / Nanie ","lastName":"Aquino","rated":false}],"history":[]},{"teamNumber":4,"players":[{"firstName":"Rod ","lastName":"Gumabay","rated":false},{"firstName":"Leo ","lastName":"Safoket","rated":false}],"history":[]},{"teamNumber":5,"players":[{"firstName":"Jonathan ","lastName":"Salvador","rated":false},{"firstName":"Eugene ","lastName":"Baltazar","rated":false}],"history":[]},{"teamNumber":6,"players":[{"firstName":"Max Hadloc / Louie ","lastName":"Soriano","rated":false},{"firstName":"Juni ","lastName":"Atindan","rated":false}],"history":[]},{"teamNumber":7,"players":[{"firstName":"Edgar ","lastName":"Sulayao","rated":false},{"firstName":"Aldrin ","lastName":"Laxa","rated":false}],"history":[]},{"teamNumber":8,"players":[{"firstName":"Jonathan Salvador / Bernie ","lastName":"Arciga","rated":false},{"firstName":"Bong ","lastName":"Yutuc","rated":false}],"history":[]},{"teamNumber":9,"players":[{"firstName":"Rexinor Dela ","lastName":"Cruz","rated":false},{"firstName":"Rence ","lastName":"Valdes","rated":false}],"history":[]},{"teamNumber":10,"players":[{"firstName":"Rolly ","lastName":"Salcedo","rated":false},{"firstName":"Alvin Ponce / Mark ","lastName":"Canapi","rated":false}],"history":[]},{"teamNumber":11,"players":[{"firstName":"Boxc ","lastName":"Malonzo","rated":false},{"firstName":"Pros ","lastName":"Millare","rated":false}],"history":[]},{"teamNumber":12,"players":[{"firstName":"Joel ","lastName":"Solis","rated":false},{"firstName":"Hernie Antonio / Jhay ","lastName":"Malonso","rated":false}],"history":[]},{"teamNumber":13,"players":[{"firstName":"Stefan Keskitalo / Rolly ","lastName":"Salcedo","rated":false},{"firstName":"Jofer De ","lastName":"Guzman","rated":false}],"history":[]},{"teamNumber":14,"players":[{"firstName":"Lito Lobo / Nomer ","lastName":"Gala","rated":false},{"firstName":"Edgar Sulayao / Edgardo ","lastName":"Almasco","rated":false}],"history":[]},{"teamNumber":15,"players":[{"firstName":"Noriel Belen / Jorge Cabanda ","lastName":"Jr.","rated":false},{"firstName":"Ronald De ","lastName":"Jesus","rated":false}],"history":[]},{"teamNumber":16,"players":[{"firstName":"Egay ","lastName":"Salvador","rated":false},{"firstName":"Ron ","lastName":"Salvador","rated":false}],"history":[]},{"teamNumber":17,"players":[{"firstName":"Rey ","lastName":"Rivera","rated":false},{"firstName":"sadf","lastName":"asdf","rated":false}],"history":[]},{"teamNumber":18,"players":[{"firstName":"EJ ","lastName":"Galang","rated":false},{"firstName":"Jerome ","lastName":"Velez","rated":false}],"history":[]},{"teamNumber":19,"players":[{"firstName":"Jeff Nieva / Philip ","lastName":"Koa","rated":false},{"firstName":"Sam Cadiente / Raymond ","lastName":"Solas","rated":false}],"history":[]},{"teamNumber":20,"players":[{"firstName":"Rico Ferrer / Arman ","lastName":"Reyes","rated":false},{"firstName":"Chris Andrada / Jeffrey ","lastName":"Galura","rated":false}],"history":[]},{"teamNumber":21,"players":[{"firstName":"Raymond ","lastName":"Solas","rated":false},{"firstName":"Bob Talavera / Boy ","lastName":"Gonson","rated":false}],"history":[]},{"teamNumber":22,"players":[{"firstName":"Jeffrey ","lastName":"Galura","rated":false},{"firstName":"Louie ","lastName":"Soriano","rated":false}],"history":[]},{"teamNumber":23,"players":[{"firstName":"Ener Tuazon / Jhoe ","lastName":"Baylon","rated":false},{"firstName":"Jun ","lastName":"Amen","rated":false}],"history":[]},{"teamNumber":24,"players":[{"firstName":"Lito ","lastName":"Lobo","rated":false},{"firstName":"Cesar Visitacion / Jun ","lastName":"Contiling","rated":false}],"history":[]},{"teamNumber":25,"players":[{"firstName":"Rod Gumabay / Val ","lastName":"Capuyan","rated":false},{"firstName":"Nico Amen / Ronan ","lastName":"Tom","rated":false}],"history":[]},{"teamNumber":26,"players":[{"firstName":"Jun ","lastName":"Contiling","rated":false},{"firstName":"Renato Baron ","lastName":"Jr.","rated":false}],"history":[]},{"teamNumber":27,"players":[{"firstName":"Rey Colle / Pros ","lastName":"Millare","rated":false},{"firstName":"Rico ","lastName":"Ferrer","rated":false}],"history":[]},{"teamNumber":28,"players":[{"firstName":"Armand ","lastName":"Trinidad","rated":false},{"firstName":"James ","lastName":"Barcenas","rated":false}],"history":[]},{"teamNumber":29,"players":[{"firstName":"Henry ","lastName":"Suerto","rated":false},{"firstName":"Renato Baron Jr. / Prussian ","lastName":"Arcenio","rated":false}],"history":[]},{"teamNumber":30,"players":[{"firstName":"Lheo ","lastName":"Naldo","rated":false},{"firstName":"Jomar ","lastName":"Lizada","rated":false}],"history":[]},{"teamNumber":31,"players":[{"firstName":"Omi ","lastName":"Germo","rated":false},{"firstName":"b","lastName":"","rated":false}],"history":[]},{"teamNumber":32,"players":[{"firstName":"Jerome Velez / Dennis ","lastName":"Prado","rated":false},{"firstName":"Pipo ","lastName":"Garcia","rated":false}],"history":[]},{"teamNumber":33,"players":[{"firstName":"Ed ","lastName":"Paringit","rated":false},{"firstName":"Ronnie ","lastName":"Jalaman","rated":false}],"history":[]},{"teamNumber":34,"players":[{"firstName":"Mhike Esposo / Rodel ","lastName":"Guiao","rated":false},{"firstName":"Daryl ","lastName":"Leano","rated":false}],"history":[]},{"teamNumber":35,"players":[{"firstName":"Gabby ","lastName":"Fajardo","rated":false},{"firstName":"Arnold ","lastName":"Ramos","rated":false}],"history":[]},{"teamNumber":36,"players":[{"firstName":"Jeffrey ","lastName":"Roxas","rated":false},{"firstName":"Alvin ","lastName":"Mallillin","rated":false}],"history":[]},{"teamNumber":37,"players":[{"firstName":"Virgilio ","lastName":"Morales","rated":false},{"firstName":"Karl Yambao / Rocky ","lastName":"Domingo","rated":false}],"history":[]},{"teamNumber":38,"players":[{"firstName":"Jeorge ","lastName":"Alcayaga","rated":false},{"firstName":"Jeffrey Roxas / Omi ","lastName":"Germo","rated":false}],"history":[]},{"teamNumber":39,"players":[{"firstName":"Jonathan ","lastName":"Cabanada","rated":false},{"firstName":"Jhoe ","lastName":"Baylon","rated":false}],"history":[]},{"teamNumber":40,"players":[{"firstName":"Arman ","lastName":"Sacal","rated":false},{"firstName":"Carlito Biteng ","lastName":"Jr.","rated":false}],"history":[]},{"teamNumber":41,"players":[{"firstName":"Edgardo ","lastName":"Almasco","rated":false},{"firstName":"Mark ","lastName":"Canapi","rated":false}],"history":[]},{"teamNumber":42,"players":[{"firstName":"Bernie ","lastName":"Arciga","rated":false},{"firstName":"Stefan ","lastName":"Keskitalo","rated":false}],"history":[]},{"teamNumber":43,"players":[{"firstName":"Bong Yutuc / Edward ","lastName":"Yara","rated":false},{"firstName":"Dennis ","lastName":"Prado","rated":false}],"history":[]},{"teamNumber":44,"players":[{"firstName":"Armand Trinidad / Mike ","lastName":"Felix","rated":false},{"firstName":"Val ","lastName":"Capuyan","rated":false}],"history":[]},{"teamNumber":45,"players":[{"firstName":"Alain ","lastName":"Abiabi","rated":false},{"firstName":"Roger ","lastName":"Canonilo","rated":false}],"history":[]},{"teamNumber":46,"players":[{"firstName":"Chris ","lastName":"Andrada","rated":false},{"firstName":"Gabby Fajardo / Egay ","lastName":"Salvador","rated":false}],"history":[]},{"teamNumber":47,"players":[{"firstName":"Ronald De Jesus / Jonathan ","lastName":"Cabanada","rated":false},{"firstName":"Nanie ","lastName":"Aquino","rated":false}],"history":[]},{"teamNumber":48,"players":[{"firstName":"Noriel ","lastName":"Belen","rated":false},{"firstName":"Max ","lastName":"Hadloc","rated":false}],"history":[]},{"teamNumber":49,"players":[{"firstName":"Jhay ","lastName":"Malonso","rated":false},{"firstName":"Jomel Balbin / Virgilio ","lastName":"Morales","rated":false}],"history":[]},{"teamNumber":50,"players":[{"firstName":"Boy ","lastName":"Gonson","rated":false},{"firstName":"Jeorge Alcayaga / Paolo ","lastName":"Nebrida","rated":false}],"history":[]},{"teamNumber":51,"players":[{"firstName":"Bhong ","lastName":"Samberi","rated":false},{"firstName":"Jeff ","lastName":"Nieva","rated":false}],"history":[]},{"teamNumber":52,"players":[{"firstName":"Nico ","lastName":"Amen","rated":false},{"firstName":"Philip ","lastName":"Koa","rated":false}],"history":[]},{"teamNumber":53,"players":[{"firstName":"Rodel ","lastName":"Guiao","rated":false},{"firstName":"Paolo ","lastName":"Nebrida","rated":false}],"history":[]},{"teamNumber":54,"players":[{"firstName":"Juni Atindan / Leo ","lastName":"Safoket","rated":false},{"firstName":"Jun Amen / Dindo ","lastName":"Evangelista","rated":false}],"history":[]},{"teamNumber":55,"players":[{"firstName":"Sonny ","lastName":"Regidor","rated":false},{"firstName":"Jun ","lastName":"Agustin","rated":false}],"history":[]},{"teamNumber":56,"players":[{"firstName":"Jofer De Guzman / Rey ","lastName":"Rivera","rated":false},{"firstName":"Jhay R ","lastName":"Sabanal","rated":false}],"history":[]},{"teamNumber":57,"players":[{"firstName":"Rey ","lastName":"Colle","rated":false},{"firstName":"George ","lastName":"Ponce","rated":false}],"history":[]},{"teamNumber":58,"players":[{"firstName":"Aldrin Laxa / Nayr ","lastName":"Ocampo","rated":false},{"firstName":"King ","lastName":"Floresca","rated":false}],"history":[]},{"teamNumber":59,"players":[{"firstName":"Jomel ","lastName":"Balbin","rated":false},{"firstName":"King Floresca / Lheo ","lastName":"Naldo","rated":false}],"history":[]},{"teamNumber":60,"players":[{"firstName":"Rence Valdes / Bhong ","lastName":"Samberi","rated":false},{"firstName":"Jhay R Sabanal / Roy ","lastName":"Agustin","rated":false}],"history":[]},{"teamNumber":61,"players":[{"firstName":"Mac ","lastName":"Gonzales","rated":false},{"firstName":"Jomar Lizada / Nelson ","lastName":"Uligan","rated":false}],"history":[]},{"teamNumber":62,"players":[{"firstName":"Nomer ","lastName":"Gala","rated":false},{"firstName":"Ronan ","lastName":"Tom","rated":false}],"history":[]},{"teamNumber":63,"players":[{"firstName":"a","lastName":"a","rated":false},{"firstName":"Bob ","lastName":"Talavera","rated":false}],"history":[]},{"teamNumber":64,"players":[{"firstName":"Arnold Ramos / Rogel ","lastName":"Carreon","rated":false},{"firstName":"Ricky ","lastName":"Mijares","rated":false}],"history":[]},{"teamNumber":65,"players":[{"firstName":"Nats Logronio / Ronnie ","lastName":"Jalaman","rated":false},{"firstName":"Ron Salvador / Henry ","lastName":"Suerto","rated":false}],"history":[]},{"teamNumber":66,"players":[{"firstName":"Hernie ","lastName":"Antonio","rated":false},{"firstName":"Rexinor Dela Cruz / Mac ","lastName":"Gonzales","rated":false}],"history":[]},{"teamNumber":67,"players":[{"firstName":"Daryl Leano / Ed ","lastName":"Paringit","rated":false},{"firstName":"Archie ","lastName":"Limpahan","rated":false}],"history":[]},{"teamNumber":68,"players":[{"firstName":"Dindo ","lastName":"Evangelista","rated":false},{"firstName":"Ener ","lastName":"Tuazon","rated":false}],"history":[]},{"teamNumber":69,"players":[{"firstName":"Prussian ","lastName":"Arcenio","rated":false},{"firstName":"Roy ","lastName":"Agustin","rated":false}],"history":[]},{"teamNumber":70,"players":[{"firstName":"Mhike ","lastName":"Esposo","rated":false},{"firstName":"Nayr ","lastName":"Ocampo","rated":false}],"history":[]},{"teamNumber":71,"players":[{"firstName":"Arman ","lastName":"Reyes","rated":false},{"firstName":"Jun Agustin / Arman ","lastName":"Sacal","rated":false}],"history":[]},{"teamNumber":72,"players":[{"firstName":"Rocky ","lastName":"Domingo","rated":false},{"firstName":"Jorge Cabanda ","lastName":"Jr.","rated":false}],"history":[]},{"teamNumber":73,"players":[{"firstName":"Alvin Mallillin / Leo ","lastName":"Buizon","rated":false},{"firstName":"Edward ","lastName":"Yara","rated":false}],"history":[]},{"teamNumber":74,"players":[{"firstName":"Nelson ","lastName":"Uligan","rated":false},{"firstName":"Mike ","lastName":"Felix","rated":false}],"history":[]},{"teamNumber":75,"players":[{"firstName":"EJ Galang / James ","lastName":"Barcenas","rated":false},{"firstName":"Leo ","lastName":"Buizon","rated":false}],"history":[]},{"teamNumber":76,"players":[{"firstName":"Alvin ","lastName":"Ponce","rated":false},{"firstName":"Nats ","lastName":"Logronio","rated":false}],"history":[]},{"teamNumber":77,"players":[{"firstName":"Roger Canonilo / Carlito Biteng ","lastName":"Jr.","rated":false},{"firstName":"Eugene Baltazar / Pipo ","lastName":"Garcia","rated":false}],"history":[]},{"teamNumber":78,"players":[{"firstName":"Boxc Malonzo / Archie ","lastName":"Limpahan","rated":false},{"firstName":"Karl ","lastName":"Yambao","rated":false}],"history":[]}],"players":[{"firstName":"Juni Atindan / Leo ","lastName":"Safoket","rated":false},{"firstName":"Jun Amen / Dindo ","lastName":"Evangelista","rated":false},{"firstName":"Max Hadloc / Louie ","lastName":"Soriano","rated":false},{"firstName":"Bong Yutuc / Edward ","lastName":"Yara","rated":false},{"firstName":"Daryl Leano / Ed ","lastName":"Paringit","rated":false},{"firstName":"Joel Solis / Nanie ","lastName":"Aquino","rated":false},{"firstName":"Jeff Nieva / Philip ","lastName":"Koa","rated":false},{"firstName":"Rexinor Dela Cruz / Mac ","lastName":"Gonzales","rated":false},{"firstName":"Chris Andrada / Jeffrey ","lastName":"Galura","rated":false},{"firstName":"King Floresca / Lheo ","lastName":"Naldo","rated":false},{"firstName":"Sonny Regidor / Alain ","lastName":"Abiabi","rated":false},{"firstName":"Jomar Lizada / Nelson ","lastName":"Uligan","rated":false},{"firstName":"Stefan Keskitalo / Rolly ","lastName":"Salcedo","rated":false},{"firstName":"Lito Lobo / Nomer ","lastName":"Gala","rated":false},{"firstName":"Arnold Ramos / Rogel ","lastName":"Carreon","rated":false},{"firstName":"Noriel Belen / Jorge Cabanda ","lastName":"Jr.","rated":false},{"firstName":"Roger Canonilo / Carlito Biteng ","lastName":"Jr.","rated":false},{"firstName":"Boxc Malonzo / Archie ","lastName":"Limpahan","rated":false},{"firstName":"Gabby Fajardo / Egay ","lastName":"Salvador","rated":false},{"firstName":"Ener Tuazon / Jhoe ","lastName":"Baylon","rated":false},{"firstName":"Jun Agustin / Arman ","lastName":"Sacal","rated":false},{"firstName":"Rey Colle / Pros ","lastName":"Millare","rated":false},{"firstName":"Renato Baron Jr. / Prussian ","lastName":"Arcenio","rated":false},{"firstName":"Aldrin Laxa / Nayr ","lastName":"Ocampo","rated":false},{"firstName":"Rence Valdes / Bhong ","lastName":"Samberi","rated":false},{"firstName":"Karl Yambao / Rocky ","lastName":"Domingo","rated":false},{"firstName":"Rod Gumabay / Val ","lastName":"Capuyan","rated":false},{"firstName":"Hernie Antonio / Jhay ","lastName":"Malonso","rated":false},{"firstName":"Sam Cadiente / Raymond ","lastName":"Solas","rated":false},{"firstName":"Eugene Baltazar / Pipo ","lastName":"Garcia","rated":false},{"firstName":"Ronald De Jesus / Jonathan ","lastName":"Cabanada","rated":false},{"firstName":"Bob Talavera / Boy ","lastName":"Gonson","rated":false},{"firstName":"Alvin Ponce / Mark ","lastName":"Canapi","rated":false},{"firstName":"Nats Logronio / Ronnie ","lastName":"Jalaman","rated":false},{"firstName":"Rico Ferrer / Arman ","lastName":"Reyes","rated":false},{"firstName":"Armand Trinidad / Mike ","lastName":"Felix","rated":false},{"firstName":"Jonathan Salvador / Bernie ","lastName":"Arciga","rated":false},{"firstName":"Jeffrey Roxas / Omi ","lastName":"Germo","rated":false},{"firstName":"Alvin Mallillin / Leo ","lastName":"Buizon","rated":false},{"firstName":"Ron Salvador / Henry ","lastName":"Suerto","rated":false},{"firstName":"Jerome Velez / Dennis ","lastName":"Prado","rated":false},{"firstName":"Edgar Sulayao / Edgardo ","lastName":"Almasco","rated":false},{"firstName":"George Ponce / Ricky ","lastName":"Mijares","rated":false},{"firstName":"Mhike Esposo / Rodel ","lastName":"Guiao","rated":false},{"firstName":"Cesar Visitacion / Jun ","lastName":"Contiling","rated":false},{"firstName":"EJ Galang / James ","lastName":"Barcenas","rated":false},{"firstName":"Jeorge Alcayaga / Paolo ","lastName":"Nebrida","rated":false},{"firstName":"Jomel Balbin / Virgilio ","lastName":"Morales","rated":false},{"firstName":"Jhay R Sabanal / Roy ","lastName":"Agustin","rated":false},{"firstName":"Jofer De Guzman / Rey ","lastName":"Rivera","rated":false},{"firstName":"Nico Amen / Ronan ","lastName":"Tom","rated":false},{"firstName":"Aldrin ","lastName":"Laxa","rated":false},{"firstName":"Jeorge ","lastName":"Alcayaga","rated":false},{"firstName":"Mhike ","lastName":"Esposo","rated":false},{"firstName":"Jhay ","lastName":"Malonso","rated":false},{"firstName":"Arman ","lastName":"Sacal","rated":false},{"firstName":"Mike ","lastName":"Felix","rated":false},{"firstName":"EJ ","lastName":"Galang","rated":false},{"firstName":"Raymond ","lastName":"Solas","rated":false},{"firstName":"Mark ","lastName":"Canapi","rated":false},{"firstName":"Jhay R ","lastName":"Sabanal","rated":false},{"firstName":"Renato Baron ","lastName":"Jr.","rated":false},{"firstName":"Virgilio ","lastName":"Morales","rated":false},{"firstName":"Rod ","lastName":"Gumabay","rated":false},{"firstName":"Armand ","lastName":"Trinidad","rated":false},{"firstName":"Mac ","lastName":"Gonzales","rated":false},{"firstName":"Nanie ","lastName":"Aquino","rated":false},{"firstName":"Jomar ","lastName":"Lizada","rated":false},{"firstName":"Bhong ","lastName":"Samberi","rated":false},{"firstName":"Ronnie ","lastName":"Jalaman","rated":false},{"firstName":"Jonathan ","lastName":"Salvador","rated":false},{"firstName":"Rence ","lastName":"Valdes","rated":false},{"firstName":"Jerome ","lastName":"Velez","rated":false},{"firstName":"Rocky ","lastName":"Domingo","rated":false},{"firstName":"Rogel ","lastName":"Carreon","rated":false},{"firstName":"Arnold ","lastName":"Ramos","rated":false},{"firstName":"Gabby ","lastName":"Fajardo","rated":false},{"firstName":"Eugene ","lastName":"Baltazar","rated":false},{"firstName":"Jorge Cabanda ","lastName":"Jr.","rated":false},{"firstName":"Noriel ","lastName":"Belen","rated":false},{"firstName":"Carlito Biteng ","lastName":"Jr.","rated":false},{"firstName":"Jofer De ","lastName":"Guzman","rated":false},{"firstName":"Ronan ","lastName":"Tom","rated":false},{"firstName":"Sonny ","lastName":"Regidor","rated":false},{"firstName":"Dennis ","lastName":"Prado","rated":false},{"firstName":"Paolo ","lastName":"Nebrida","rated":false},{"firstName":"Stefan ","lastName":"Keskitalo","rated":false},{"firstName":"Chris ","lastName":"Andrada","rated":false},{"firstName":"Roger ","lastName":"Canonilo","rated":false},{"firstName":"Jeffrey ","lastName":"Roxas","rated":false},{"firstName":"Max ","lastName":"Hadloc","rated":false},{"firstName":"Juni ","lastName":"Atindan","rated":false},{"firstName":"Rexinor Dela ","lastName":"Cruz","rated":false},{"firstName":"Bong ","lastName":"Yutuc","rated":false},{"firstName":"Daryl ","lastName":"Leano","rated":false},{"firstName":"Egay ","lastName":"Salvador","rated":false},{"firstName":"Jonathan ","lastName":"Cabanada","rated":false},{"firstName":"Rolly ","lastName":"Salcedo","rated":false},{"firstName":"Rey ","lastName":"Rivera","rated":false},{"firstName":"Nomer ","lastName":"Gala","rated":false},{"firstName":"Bob ","lastName":"Talavera","rated":false},{"firstName":"Cesar ","lastName":"Visitacion","rated":false},{"firstName":"Jhoe ","lastName":"Baylon","rated":false},{"firstName":"Lheo ","lastName":"Naldo","rated":false},{"firstName":"Ener ","lastName":"Tuazon","rated":false},{"firstName":"Sam ","lastName":"Cadiente","rated":false},{"firstName":"Roy ","lastName":"Agustin","rated":false},{"firstName":"Archie ","lastName":"Limpahan","rated":false},{"firstName":"Ronald De ","lastName":"Jesus","rated":false},{"firstName":"Jun ","lastName":"Agustin","rated":false},{"firstName":"Nelson ","lastName":"Uligan","rated":false},{"firstName":"Alain ","lastName":"Abiabi","rated":false},{"firstName":"James ","lastName":"Barcenas","rated":false},{"firstName":"Leo ","lastName":"Safoket","rated":false},{"firstName":"Val ","lastName":"Capuyan","rated":false},{"firstName":"Jun ","lastName":"Contiling","rated":false},{"firstName":"Ron ","lastName":"Salvador","rated":false},{"firstName":"Edward ","lastName":"Yara","rated":false},{"firstName":"Boy ","lastName":"Gonson","rated":false},{"firstName":"Prussian ","lastName":"Arcenio","rated":false},{"firstName":"Pipo ","lastName":"Garcia","rated":false},{"firstName":"Philip ","lastName":"Koa","rated":false},{"firstName":"Ricky ","lastName":"Mijares","rated":false},{"firstName":"Jun ","lastName":"Amen","rated":false},{"firstName":"Nico ","lastName":"Amen","rated":false},{"firstName":"Rico ","lastName":"Ferrer","rated":false},{"firstName":"Louie ","lastName":"Soriano","rated":false},{"firstName":"Hernie ","lastName":"Antonio","rated":false},{"firstName":"Nayr ","lastName":"Ocampo","rated":false},{"firstName":"Leo ","lastName":"Buizon","rated":false},{"firstName":"Omi ","lastName":"Germo","rated":false},{"firstName":"King ","lastName":"Floresca","rated":false},{"firstName":"Pros ","lastName":"Millare","rated":false},{"firstName":"Jeffrey ","lastName":"Galura","rated":false},{"firstName":"Boxc ","lastName":"Malonzo","rated":false},{"firstName":"Jeff ","lastName":"Nieva","rated":false},{"firstName":"Edgar ","lastName":"Sulayao","rated":false},{"firstName":"Lito ","lastName":"Lobo","rated":false},{"firstName":"Karl ","lastName":"Yambao","rated":false},{"firstName":"Arman ","lastName":"Reyes","rated":false},{"firstName":"Rodel ","lastName":"Guiao","rated":false},{"firstName":"George ","lastName":"Ponce","rated":false},{"firstName":"Alvin ","lastName":"Ponce","rated":false},{"firstName":"Ed ","lastName":"Paringit","rated":false},{"firstName":"Jomel ","lastName":"Balbin","rated":false},{"firstName":"Bernie ","lastName":"Arciga","rated":false},{"firstName":"Nats ","lastName":"Logronio","rated":false},{"firstName":"Joel ","lastName":"Solis","rated":false},{"firstName":"Rey ","lastName":"Colle","rated":false},{"firstName":"Dindo ","lastName":"Evangelista","rated":false},{"firstName":"Edgardo ","lastName":"Almasco","rated":false},{"firstName":"Henry ","lastName":"Suerto","rated":false},{"firstName":"Alvin ","lastName":"Mallillin","rated":false},{"firstName":"sadf","lastName":"asdf","rated":false},{"firstName":"a","lastName":"a","rated":false},{"firstName":"b","lastName":"","rated":false}],"boards":[{"boardNumber":1,"matchNumber":1,"playerOne":66,"playerTwo":67,"isPrinted":true},{"boardNumber":2,"matchNumber":5,"playerOne":6,"playerTwo":7,"isPrinted":true},{"boardNumber":3,"matchNumber":7,"playerOne":8,"playerTwo":9,"isPrinted":false},{"boardNumber":4,"matchNumber":0,"playerOne":0,"playerTwo":0,"isPrinted":false},{"boardNumber":5,"matchNumber":0,"playerOne":0,"playerTwo":0,"isPrinted":false},{"boardNumber":6,"matchNumber":0,"playerOne":0,"playerTwo":0,"isPrinted":false},{"boardNumber":7,"matchNumber":0,"playerOne":0,"playerTwo":0,"isPrinted":false},{"boardNumber":8,"matchNumber":0,"playerOne":0,"playerTwo":0,"isPrinted":false},{"boardNumber":9,"matchNumber":0,"playerOne":0,"playerTwo":0,"isPrinted":false},{"boardNumber":10,"matchNumber":0,"playerOne":0,"playerTwo":0,"isPrinted":false}]}